dynamocharlotte/__init__.py
dynamocharlotte/dynamo_charlotte_source.py
dynamocharlotte/parsetab.py
dynamocharlotte/tempCodeRunnerFile.py
dynamocharlotte/ply/__init__.py
dynamocharlotte/ply/cpp.py
dynamocharlotte/ply/ctokens.py
dynamocharlotte/ply/lex.py
dynamocharlotte/ply/yacc.py
dynamocharlotte/ply/ygen.py
dynamocharlotte-0.0.1.dist-info/METADATA
dynamocharlotte-0.0.1.dist-info/WHEEL
dynamocharlotte-0.0.1.dist-info/top_level.txt
dynamocharlotte-0.0.1.dist-info/RECORD
